{
  "name": "Panasonic_S1H_Laowa 12mm f2.8 Zero-D_FHD Super35_1080p_16by9_1920x1080-119.88fps",
  "note": "10bit 4:2:0",
  "calibrated_by": "Ryan Jackson",
  "camera_brand": "Panasonic",
  "camera_model": "S1H",
  "lens_model": "Laowa 12mm f2.8 Zero-D",
  "camera_setting": "FHD Super35",
  "calib_dimension": {
    "w": 1920,
    "h": 1080
  },
  "orig_dimension": {
    "w": 1920,
    "h": 1080
  },
  "output_dimension": {
    "w": 1920,
    "h": 1080
  },
  "frame_readout_time": null,
  "gyro_lpf": null,
  "input_horizontal_stretch": 1.0,
  "input_vertical_stretch": 1.0,
  "num_images": 15,
  "fps": 119.880119,
  "crop": null,
  "official": false,
  "asymmetrical": false,
  "fisheye_params": {
    "RMS_error": 0.29439421730890475,
    "camera_matrix": [
      [
        1012.8974514169836,
        0.0,
        955.0165757438268
      ],
      [
        0.0,
        1012.1315510986888,
        534.1521775687872
      ],
      [
        0.0,
        0.0,
        1.0
      ]
    ],
    "distortion_coeffs": [
      0.3296942481052124,
      0.05129039516987616,
      0.42656120819326615,
      -0.4258919140282084
    ],
    "radial_distortion_limit": null
  },
  "identifier": "",
  "calibrator_version": "1.5.4",
  "date": "2024-01-09",
  "compatible_settings": [],
  "sync_settings": null,
  "distortion_model": null,
  "digital_lens": null,
  "digital_lens_params": null,
  "interpolations": null,
  "focal_length": null,
  "crop_factor": null,
  "global_shutter": false
}