{
  "name": "Sony_a7C_SEL2070G_@20MM_4k_16by9_3840x2160-29.97fps",
  "note": "",
  "calibrated_by": "xuyiyang",
  "camera_brand": "Sony",
  "camera_model": "a7C",
  "lens_model": "SEL2070G",
  "camera_setting": "@20MM",
  "calib_dimension": {
    "w": 3840,
    "h": 2160
  },
  "orig_dimension": {
    "w": 3840,
    "h": 2160
  },
  "output_dimension": {
    "w": 3840,
    "h": 2160
  },
  "frame_readout_time": null,
  "gyro_lpf": null,
  "input_horizontal_stretch": 1.0,
  "input_vertical_stretch": 1.0,
  "num_images": 11,
  "fps": 29.97003,
  "crop": null,
  "official": false,
  "asymmetrical": false,
  "fisheye_params": {
    "RMS_error": 0.9193131100750624,
    "camera_matrix": [
      [
        2572.164669609139,
        0.0,
        1914.03625141571
      ],
      [
        0.0,
        2567.683703799056,
        1082.8194236692682
      ],
      [
        0.0,
        0.0,
        1.0
      ]
    ],
    "distortion_coeffs": [
      0.316994606398426,
      -0.0739245651377686,
      1.0573602708406258,
      -1.4674336569205262
    ],
    "radial_distortion_limit": null
  },
  "identifier": "sony-ilce-7c-cbe22173-3840x2160@29970",
  "calibrator_version": "1.5.4",
  "date": "2024-02-25",
  "compatible_settings": [],
  "sync_settings": null,
  "distortion_model": null,
  "digital_lens": null,
  "digital_lens_params": null,
  "interpolations": null,
  "focal_length": null,
  "crop_factor": null,
  "global_shutter": false
}