{
  "name": "RED_KOMODO-X 6K S35_SIRUI Night Walker T1.2  55mm_6K_5k_16by9_5760x3240-50.00fps",
  "note": "",
  "calibrated_by": "改二",
  "camera_brand": "RED",
  "camera_model": "KOMODO-X 6K S35",
  "lens_model": "SIRUI Night Walker T1.2  55mm",
  "camera_setting": "6K",
  "calib_dimension": {
    "w": 5760,
    "h": 3240
  },
  "orig_dimension": {
    "w": 5760,
    "h": 3240
  },
  "output_dimension": {
    "w": 5760,
    "h": 3240
  },
  "frame_readout_time": null,
  "gyro_lpf": null,
  "input_horizontal_stretch": 1.0,
  "input_vertical_stretch": 1.0,
  "num_images": 15,
  "fps": 50.0,
  "crop": null,
  "official": false,
  "asymmetrical": false,
  "fisheye_params": {
    "RMS_error": 1.069629334792486,
    "camera_matrix": [
      [
        13793.750739575353,
        0.0,
        2938.731422204289
      ],
      [
        0.0,
        13794.000118333684,
        1616.1231460763142
      ],
      [
        0.0,
        0.0,
        1.0
      ]
    ],
    "distortion_coeffs": [
      0.7379826088713031,
      3.4300840679360296,
      -33.442781464216544,
      20.02069588290343
    ],
    "radial_distortion_limit": null
  },
  "identifier": "",
  "calibrator_version": "1.5.4",
  "date": "",
  "compatible_settings": [],
  "sync_settings": null,
  "distortion_model": null,
  "digital_lens": null,
  "digital_lens_params": null,
  "interpolations": null,
  "focal_length": 55.0,
  "crop_factor": 1.33,
  "global_shutter": true
}