{
  "name": "RED_KOMODO 6K_Irix 21mm_17:9_C4k_1.90by1_4096x2160-25.00fps",
  "note": "Canon X0.71",
  "calibrated_by": "Shikijo",
  "camera_brand": "RED",
  "camera_model": "KOMODO 6K",
  "lens_model": "Irix 21mm",
  "camera_setting": "17:9",
  "calib_dimension": {
    "w": 4096,
    "h": 2160
  },
  "orig_dimension": {
    "w": 4096,
    "h": 2160
  },
  "output_dimension": {
    "w": 4096,
    "h": 2160
  },
  "frame_readout_time": null,
  "gyro_lpf": null,
  "input_horizontal_stretch": 1.0,
  "input_vertical_stretch": 1.0,
  "num_images": 15,
  "fps": 25.0,
  "crop": null,
  "official": false,
  "asymmetrical": false,
  "fisheye_params": {
    "RMS_error": 0.8921860824904838,
    "camera_matrix": [
      [
        3602.004834617482,
        0.0,
        2096.4502183663567
      ],
      [
        0.0,
        3602.211488324293,
        1037.9183788812895
      ],
      [
        0.0,
        0.0,
        1.0
      ]
    ],
    "distortion_coeffs": [
      0.24343321797305817,
      0.25851365319111896,
      -0.4153414599686365,
      1.0086058909543232
    ],
    "radial_distortion_limit": null
  },
  "identifier": "",
  "calibrator_version": "1.5.4",
  "date": "",
  "compatible_settings": [],
  "sync_settings": null,
  "distortion_model": null,
  "digital_lens": null,
  "digital_lens_params": null,
  "interpolations": null,
  "focal_length": null,
  "crop_factor": null,
  "global_shutter": true
}