{
  "name": "RED_KOMODO 6K_7Artisans 50mm T2.0 @6K_6K 17:9_6k_1.90by1_6144x3240-24.00fps",
  "note": "",
  "calibrated_by": "Volki",
  "camera_brand": "RED",
  "camera_model": "KOMODO 6K",
  "lens_model": "7Artisans 50mm T2.0 @6K",
  "camera_setting": "6K 17:9",
  "calib_dimension": {
    "w": 6144,
    "h": 3240
  },
  "orig_dimension": {
    "w": 6144,
    "h": 3240
  },
  "output_dimension": {
    "w": 6144,
    "h": 3240
  },
  "frame_readout_time": null,
  "gyro_lpf": null,
  "input_horizontal_stretch": 1.0,
  "input_vertical_stretch": 1.0,
  "num_images": 10,
  "fps": 24.0,
  "crop": null,
  "official": false,
  "asymmetrical": false,
  "fisheye_params": {
    "RMS_error": 1.3723776482777417,
    "camera_matrix": [
      [
        10043.200324699275,
        0.0,
        3067.865477863019
      ],
      [
        0.0,
        10037.739355425188,
        1610.6069595552844
      ],
      [
        0.0,
        0.0,
        1.0
      ]
    ],
    "distortion_coeffs": [
      0.11028924496682016,
      8.192795247937948,
      -182.52009714825616,
      1374.5598348066476
    ],
    "radial_distortion_limit": null
  },
  "identifier": "",
  "calibrator_version": "1.5.2",
  "date": "2023-09-29",
  "compatible_settings": [],
  "sync_settings": null,
  "distortion_model": null,
  "digital_lens": null,
  "digital_lens_params": null,
  "interpolations": null,
  "focal_length": null,
  "crop_factor": null,
  "global_shutter": false
}